ida_db/__init__.py
ida_db/ida_db.py
ida_db-2025.2.17.1841.dist-info/LICENSE
ida_db-2025.2.17.1841.dist-info/METADATA
ida_db-2025.2.17.1841.dist-info/WHEEL
ida_db-2025.2.17.1841.dist-info/top_level.txt
ida_db-2025.2.17.1841.dist-info/RECORD
